Datey/Datey.py
Datey/__init__.py
Datey-0.0.1.dist-info/LICENSE
Datey-0.0.1.dist-info/METADATA
Datey-0.0.1.dist-info/WHEEL
Datey-0.0.1.dist-info/top_level.txt
Datey-0.0.1.dist-info/RECORD
