Metadata-Version: 2.1
Name: Datey
Version: 0.0.1
Summary: Use module for your program
Home-page: https://github.com/33f44
Author: irakli googoochani
Author-email: irakligoogoochaniv@gmail.com
License: UNKNOWN
Platform: UNKNOWN
Classifier: Programming Language :: Python :: 3
Classifier: License :: OSI Approved :: MIT License
Classifier: Operating System :: OS Independent
Requires-Python: >=3.8
